dimwiddle/__init__.py
dimwiddle/_version.py
dimwiddle/application/__init__.py
dimwiddle/application/load_definitions.py
dimwiddle/application/module_resolution.py
dimwiddle/application/protocols/__init__.py
dimwiddle/application/protocols/config_protocol.py
dimwiddle/application/protocols/yaml_loader_protocol.py
dimwiddle/domain/__init__.py
dimwiddle/domain/container.py
dimwiddle/domain/service_definition.py
dimwiddle/infrastructure/__init__.py
dimwiddle/infrastructure/config.py
dimwiddle/infrastructure/tagged_iterator.py
dimwiddle/infrastructure/yaml_loader.py
dimwiddle-0.1.2.dist-info/METADATA
dimwiddle-0.1.2.dist-info/WHEEL
dimwiddle-0.1.2.dist-info/top_level.txt
dimwiddle-0.1.2.dist-info/RECORD
