Metadata-Version: 2.4
Name: dimwiddle
Version: 0.1.2
Summary: A lightweight dependency injection framework inspired by Symfony
Author-email: Dimwiddle Contributors <example@example.com>
License: MIT
Project-URL: Homepage, https://github.com/example/dimwiddle
Project-URL: Bug Tracker, https://github.com/example/dimwiddle/issues
Classifier: Programming Language :: Python :: 3
Classifier: Programming Language :: Python :: 3.8
Classifier: Programming Language :: Python :: 3.9
Classifier: Programming Language :: Python :: 3.10
Classifier: Programming Language :: Python :: 3.11
Classifier: Operating System :: OS Independent
Classifier: Intended Audience :: Developers
Classifier: Topic :: Software Development :: Libraries :: Application Frameworks
Requires-Python: >=3.8
Requires-Dist: pyyaml>=6.0
Requires-Dist: python-dotenv>=1.0.0
Requires-Dist: requests>=2.25.0
